claude_progress_guardian_mcp-1.0.0.dist-info/licenses/LICENSE
smart_timeout_mcp/__init__.py
smart_timeout_mcp/progress_monitor.py
smart_timeout_mcp/smart_timeout.py
claude_progress_guardian_mcp-1.0.0.dist-info/METADATA
claude_progress_guardian_mcp-1.0.0.dist-info/WHEEL
claude_progress_guardian_mcp-1.0.0.dist-info/entry_points.txt
claude_progress_guardian_mcp-1.0.0.dist-info/top_level.txt
claude_progress_guardian_mcp-1.0.0.dist-info/RECORD
