Metadata-Version: 2.4
Name: claude-progress-guardian-mcp
Version: 1.0.0
Summary: Prevents infinite progress bar spam in Claude Code with intelligent timeout management
Home-page: https://github.com/yscha88/claude-progress-guardian-mcp
Author: yscha88
Author-email: clmfkilu@gmail.com
Project-URL: Bug Reports, https://github.com/yscha88/claude-progress-guardian-mcp/issues
Project-URL: Source, https://github.com/yscha88/claude-progress-guardian-mcp
Project-URL: Documentation, https://github.com/yscha88/claude-progress-guardian-mcp/wiki
Keywords: claude,code,progress,bar,spam,timeout,mcp,guardian,monitoring
Classifier: Development Status :: 4 - Beta
Classifier: Intended Audience :: Developers
Classifier: License :: OSI Approved :: MIT License
Classifier: Operating System :: OS Independent
Classifier: Programming Language :: Python :: 3
Classifier: Programming Language :: Python :: 3.8
Classifier: Programming Language :: Python :: 3.9
Classifier: Programming Language :: Python :: 3.10
Classifier: Programming Language :: Python :: 3.11
Classifier: Topic :: Software Development :: Libraries :: Python Modules
Classifier: Topic :: System :: Monitoring
Classifier: Topic :: System :: Systems Administration
Classifier: Topic :: Utilities
Classifier: Framework :: AsyncIO
Requires-Python: >=3.8
License-File: LICENSE
Requires-Dist: asyncio
Requires-Dist: dataclasses; python_version < "3.7"
Provides-Extra: dev
Requires-Dist: pytest>=7.0; extra == "dev"
Requires-Dist: black>=22.0; extra == "dev"
Requires-Dist: flake8>=4.0; extra == "dev"
Requires-Dist: mypy>=0.950; extra == "dev"
Dynamic: author
Dynamic: author-email
Dynamic: classifier
Dynamic: description
Dynamic: description-content-type
Dynamic: home-page
Dynamic: keywords
Dynamic: license-file
Dynamic: project-url
Dynamic: provides-extra
Dynamic: requires-dist
Dynamic: requires-python
Dynamic: summary
